accordo/__init__.py
accordo-0.0.1.dist-info/WHEEL
accordo-0.0.1.dist-info/METADATA
accordo-0.0.1.dist-info/RECORD
