Metadata-Version: 2.1
Name: accordo
Version: 0.0.1
Summary: Deep Learning experiment orchestration tool
Author: rcmalli
Author-email: refikcanmalli@gmail.com
Requires-Python: >=3.8,<4.0
Classifier: Programming Language :: Python :: 3
Classifier: Programming Language :: Python :: 3.8
Classifier: Programming Language :: Python :: 3.9
Classifier: Programming Language :: Python :: 3.10
